Workbook
Name ContractorName: Cover!$B$5
Name FiscalYearEnd: Cover!$B$6
Name FringeRate: 'Indirect Pools'!$C$5/'Direct Labor'!$F$11
Name GARate: 'Indirect Pools'!$C$13/('Direct Labor'!$F$11+'Indirect Pools'!$C$5+'Indirect Pools'!$C$9)
Name IndirectPools: 'Indirect Pools'!$A$5:$D$17
Name OverheadRate: 'Indirect Pools'!$C$9/'Direct Labor'!$F$11
Name PreparedBy: Cover!$B$7

Sheet Cover
A1: Incurred Cost Electronic Submission
A2: Prepared in accordance with FAR 52.216-7(d)(2) - Schedules H, H-1 and supporting pools
A5: Contractor | B5: Northwind Defense Systems, Inc.
A6: Fiscal year end | B6: 46022
A7: Prepared by | B7: J. Alvarez, Controller
A8: Submission date | B8: {{submissionDate}}
A10: Yellow cells are inputs. All other cells are protected.

Sheet Direct Labor
A1: Schedule: Direct Labor by Employee
A2: =ContractorName&" - FYE "&TEXT(FiscalYearEnd,"mm/dd/yyyy") -> Northwind Defense Systems, Inc. - FYE 12/31/2025
A4: Employee | B4: LaborCategory | C4: Project | D4: Hours | E4: Rate | F4: Cost
A5: Maria Chen | B5: Senior Engineer | C5: W56HZV-24-C-0112 | D5: 1880 | E5: 72.5 | F5: =DirectLabor[[#This Row],[Hours]]*DirectLabor[[#This Row],[Rate]] -> 136300
A6: David Okafor | B6: Systems Analyst | C6: W56HZV-24-C-0112 | D6: 1920 | E6: 58.25 | F6: =DirectLabor[[#This Row],[Hours]]*DirectLabor[[#This Row],[Rate]] -> 111840
A7: Priya Raman | B7: Program Manager | C7: FA8650-23-D-2040 | D7: 1760 | E7: 81 | F7: =DirectLabor[[#This Row],[Hours]]*DirectLabor[[#This Row],[Rate]] -> 142560
A8: Tom Lindqvist | B8: Test Technician | C8: FA8650-23-D-2040 | D8: 2010 | E8: 39.75 | F8: =DirectLabor[[#This Row],[Hours]]*DirectLabor[[#This Row],[Rate]] -> 79897.5
A9: Angela Ruiz | B9: Software Engineer II | C9: N00024-25-C-5301 | D9: 1840 | E9: 64.1 | F9: =DirectLabor[[#This Row],[Hours]]*DirectLabor[[#This Row],[Rate]] -> 117944
A10: Kevin Brandt | B10: Technical Writer | C10: N00024-25-C-5301 | D10: 1500 | E10: 44 | F10: =DirectLabor[[#This Row],[Hours]]*DirectLabor[[#This Row],[Rate]] -> 66000
A11: Total | D11: =SUBTOTAL(109,DirectLabor[Hours]) -> 10910 | F11: =SUBTOTAL(109,DirectLabor[Cost]) -> 654541.5

Sheet Indirect Pools
A1: Schedule: Indirect Expense Pools
A2: =ContractorName -> Northwind Defense Systems, Inc.
A4: Account | B4: Description | C4: Amount | D4: Share of Total
A5: Fringe | C5: =SUM(C6:C8) -> 207740 | D5: 0.21536611
A6: 5100 | B6: Employer FICA / Medicare | C6: 50070 | D6: 0.051908065
A7: 5110 | B7: Group health insurance | C7: 118400 | D7: 0.12274645
A8: 5120 | B8: 401(k) employer match | C8: 39270 | D8: 0.040711598
A9: Overhead | C9: =SUM(C10:C12) -> 556550 | D9: 0.57698089
A10: 6100 | B10: Facilities rent | C10: 214000 | D10: 0.22185592
A11: 6110 | B11: Utilities | C11: 38650 | D11: 0.040068838
A12: 6120 | B12: Indirect labor - engineering support | C12: 303900 | D12: 0.31505614
A13: G&A | C13: =SUM(C14:C16) -> 200300 | D13: 0.20765299
A14: 7100 | B14: Executive salaries | C14: 142000 | D14: 0.14721281
A15: 7110 | B15: Accounting & legal | C15: 36500 | D15: 0.037839911
A16: 7120 | B16: General liability insurance | C16: 21800 | D16: 0.022600276
A17: Total Indirect Pools | C17: =SUM(C5,C9,C13) -> 964590 | D17: 1

Sheet Rates
A1: Schedule: Indirect Rate Computation
A2: ="Fiscal year ended "&TEXT(FiscalYearEnd,"mmmm d, yyyy") -> Fiscal year ended December 31, 2025
A4: Rate | B4: Pool Costs | C4: Allocation Base | D4: FY2025 Rate | E4: FY2024 Rate | F4: Change
A5: Fringe | B5: ='Indirect Pools'!C5 -> 207740 | C5: ='Direct Labor'!F11 -> 654541.5 | D5: =FringeRate -> 0.31738247 | E5: 0.312 | F5: =D5-E5 -> 0.0053824731
A6: Overhead | B6: ='Indirect Pools'!C9 -> 556550 | C6: ='Direct Labor'!F11 -> 654541.5 | D6: =OverheadRate -> 0.85028986 | E6: 0.874 | F6: =D6-E6 -> -0.023710141
A7: G&A | B7: ='Indirect Pools'!C13 -> 200300 | C7: ='Direct Labor'!F11+B5+B6 -> 1418831.5 | D7: =GARate -> 0.14117251 | E7: 0.139 | F7: =D7-E7 -> 0.0021725071
A9: Direct labor per table (structured) | C9: =DirectLabor[[#Totals],[Cost]] -> 654541.5
